ddlgenerator
