Metadata-Version: 1.1
Name: ddlgenerator
Version: 0.1.8.2
Summary: Generates SQL DDL that will accept Python data
Home-page: https://github.com/catherinedevlin/ddl-generator
Author: Catherine Devlin
Author-email: catherine.devlin@gmail.com
License: MIT
Keywords: ddlgenerator
Platform: UNKNOWN
Classifier: Development Status :: 2 - Pre-Alpha
Classifier: Intended Audience :: Developers
Classifier: License :: OSI Approved :: BSD License
Classifier: Natural Language :: English
Classifier: Programming Language :: Python :: 3
Classifier: Programming Language :: Python :: 3.3
